opticalutil/__init__.py
opticalutil/dwdm.py
opticalutil/power.py
opticalutil-2.2.0.dist-info/DESCRIPTION.rst
opticalutil-2.2.0.dist-info/METADATA
opticalutil-2.2.0.dist-info/RECORD
opticalutil-2.2.0.dist-info/WHEEL
opticalutil-2.2.0.dist-info/metadata.json
opticalutil-2.2.0.dist-info/pbr.json
opticalutil-2.2.0.dist-info/top_level.txt
