Metadata-Version: 2.0
Name: opticalutil
Version: 2.2.0
Summary: Support for handling optical power.
Home-page: UNKNOWN
Author: Christian Hopps
Author-email: chopps@gmail.com
License: Apache-2
Platform: UNKNOWN
